{"about_index.md":"uXzXYiMW","blog_first.md":"-QJYgyg5","blog_index.md":"BLUu4AeX","blog_tech_live.md":"zV9e93wb","blog_tech_video-encrypt.md":"CY7AyBlX","index.md":"DRSx8HmI","kb_index.md":"BAaK79lx","kb_java_blog.md":"BLVCP4W7","kb_java_cloudnative.md":"B9ACsUV8","kb_java_consul.md":"Bgxs4a8S","kb_java_graalvm.md":"CTuO3Ynh","kb_java_gradle.md":"foSTOtPa","kb_java_grafana.md":"6oGjnPeK","kb_java_idea.md":"BLBVlT4b","kb_java_index.md":"Cn0boFEg","kb_java_jdk.md":"wdBTwKZx","kb_java_jsp.md":"CS3y_tVV","kb_java_jvm.md":"Chr85-R1","kb_java_maven.md":"CH9mD63P","kb_java_oauth.md":"CELXqztZ","kb_linux_glibc.md":"C5LoHHIb","kb_linux_index.md":"CTqQvsl-","kb_linux_rhel.md":"eFkBCVtg","kb_linux_ubuntu.md":"D5sCPM3Y","kb_macos_homebrew.md":"BaRPSdzU","kb_macos_index.md":"Bff1i_20","kb_macos_sdkman.md":"c5InZZrL","kb_mariadb_install.md":"Dv-YrC6g","kb_mongo_index.md":"BUjoyN1P","kb_mongo_install.md":"DlYPXYNe","kb_mysql_config.md":"sls2G2Sk","kb_mysql_faq.md":"CthYIv89","kb_mysql_idx.md":"Dfe8tMu9","kb_mysql_index.md":"9l035Dvs","kb_mysql_install.md":"CMaGwo9E","kb_mysql_master-slave.md":"DSgfKawU","kb_pgsql_index.md":"BkjdZ7h7","kb_pgsql_install.md":"RrHFcEJm","kb_php_awesome.md":"_HWBxK17","kb_php_index.md":"A_b3ihY8","kb_python_index.md":"DJQ9A5pX","kb_redis_index.md":"C4jMLUj7","kb_redis_install.md":"ySnOAt_s","kb_ruby_index.md":"vHMN7SiU","kb_rust_index.md":"14sI6Dc-","kb_tools_docker.md":"BgVgyxJn","kb_tools_editor.md":"BPty1hPi","kb_tools_elastic.md":"C3rUN_HX","kb_tools_git.md":"B9gMJon2","kb_tools_github.md":"BSHNUKoY","kb_tools_gitlab.md":"Kl_gGsFD","kb_tools_grafana.md":"CoglflEa","kb_tools_jenkins.md":"tEwc-Kkx","kb_tools_jmeter.md":"9ryvu5tH","kb_tools_kafka.md":"C6kBWwJ5","kb_tools_libreoffice.md":"U_wjVftk","kb_tools_nginx.md":"DlpxZIqS","kb_tools_onlyoffice.md":"CfpdmWpR","kb_tools_podman.md":"wfEr5KHm","kb_tools_rabbitmq.md":"D7Xg4pL0","kb_tools_rust-desk.md":"C_RI4xuu","kb_tools_selenium.md":"BcZfrKlp","kb_tools_storage.md":"D0r0W2tG","kb_tools_terminal.md":"CFNr1iDk","kb_web_capacitor.md":"CQPmPKo0","kb_web_ionic.md":"BzlXnmI4","kb_web_node.md":"sjqHU68s","kb_windows_index.md":"DirjohRE","kb_windows_powershell.md":"B2QTOwkH","kb_windows_vs.md":"Y7QLfH0s","kb_windows_wsl.md":"BDxiZYhd"}
