{"blog_first.md":"54033ef0","about_index.md":"c5db478b","index.md":"fc0aa35c","kb_amqp_index.md":"15d82651","kb_amqp_rabbitmq.md":"e34fe056","blog_tech_video-encrypt.md":"b29fe9f3","blog_index.md":"bc7deb24","kb_cloud_docker.md":"cf678567","blog_tech_live.md":"40a8bbe4","kb_ruby_index.md":"8fb60ca3","kb_cloud_index.md":"2d970974","kb_docs_index.md":"78bcca41","kb_docs_libreoffice.md":"b10ad601","kb_elastic_index.md":"bd48e3a1","kb_elastic_install.md":"f5c1a45a","kb_java_index.md":"cbddb820","kb_java_maven.md":"035ce996","kb_linux_index.md":"b9589fea","kb_linux_rhel.md":"9a0f19d0","kb_linux_ubuntu.md":"6a445b52","kb_macos_homebrew.md":"8da2e8a4","kb_macos_index.md":"08ce997b","kb_mongo_index.md":"6d20cfb3","kb_mongo_install.md":"52c7044b","kb_mysql_idx.md":"49901baf","kb_mysql_index.md":"683d6bfe","kb_mysql_install.md":"dbc1851b","kb_mysql_master-slave.md":"7cff574c","kb_php_awesome.md":"cf61c5e6","kb_php_index.md":"4cde5369","kb_postgresql_index.md":"04e7113f","kb_postgresql_install.md":"26925328","kb_redis_index.md":"5d06ed52","kb_redis_install.md":"560f5eed","kb_docs_onlyoffice.md":"cd0073a1","kb_rust_index.md":"6be7e53c","kb_server_index.md":"a9cea23d","kb_server_nginx.md":"ae41144c","kb_tools_git.md":"fa22a82a","kb_web_index.md":"4e2de27d","kb_web_ionic.md":"44f2ca15","kb_web_node.md":"58bb8421","kb_windows_index.md":"38cf12d7","kb_windows_powershell.md":"baa0861b","kb_windows_vs.md":"269ad876","kb_windows_wsl.md":"72adde6a","kb_amqp_kafka.md":"cb28166f","kb_java_jdk.md":"cde389f7","kb_java_jsp.md":"a5e9e29a","kb_index.md":"ac019031","kb_java_graalvm.md":"ad83d34a","kb_java_gradle.md":"9fd20676"}
