{"about_index.md":"CFEH2atz","blog_first.md":"BlsKgmDS","blog_index.md":"DXChrZhl","blog_tech_live.md":"DxibdxNn","blog_tech_video-encrypt.md":"BBEjwbmX","index.md":"axiyBgEK","kb_index.md":"Ck_ZyIAH","kb_java_blog.md":"B3vFPttx","kb_java_cloudnative.md":"BE5LAbuP","kb_java_consul.md":"DzAiOWT4","kb_java_graalvm.md":"BXGBPFhS","kb_java_gradle.md":"DhGBhuT_","kb_java_grafana.md":"x3CdHtV_","kb_java_idea.md":"C3PDNwLn","kb_java_index.md":"CgxGTb34","kb_java_jdk.md":"CMbZxOtQ","kb_java_jsp.md":"BvtSKTZv","kb_java_jvm.md":"Cv-cFoHp","kb_java_maven.md":"gv93bdJo","kb_java_oauth.md":"DGZrQna1","kb_linux_glibc.md":"D1k-vA7S","kb_linux_index.md":"yHBXUvVn","kb_linux_rhel.md":"U_8sOC_2","kb_linux_ubuntu.md":"B9pVzWOZ","kb_macos_homebrew.md":"0mmyt3gt","kb_macos_index.md":"BKMmYMHd","kb_macos_sdkman.md":"Bjd1ihch","kb_mongo_index.md":"Dm7fRtBa","kb_mongo_install.md":"B15oqxml","kb_mysql_config.md":"CJViLCkT","kb_mysql_faq.md":"C9DEFxiZ","kb_mysql_idx.md":"CnVyt7-W","kb_mysql_index.md":"mBSiemT8","kb_mysql_install.md":"DI90AaYL","kb_mysql_master-slave.md":"Cz3kV8uX","kb_pgsql_index.md":"rRl-n0bJ","kb_pgsql_install.md":"BOhwefmr","kb_php_awesome.md":"D-6cADnk","kb_php_index.md":"CJ7xSoSk","kb_python_index.md":"NPbU1ILy","kb_redis_index.md":"QZLYYAai","kb_redis_install.md":"BJnWkkXs","kb_ruby_index.md":"DVZsoVeC","kb_rust_index.md":"b6-_tjrP","kb_tools_docker.md":"CMIsVnkI","kb_tools_editor.md":"BovOroCt","kb_tools_elastic.md":"ReL8RpNY","kb_tools_git.md":"DtLN8G66","kb_tools_github.md":"CCuUsCIa","kb_tools_gitlab.md":"BGlzgba9","kb_tools_grafana.md":"Dkwdmi-C","kb_tools_jenkins.md":"DCpOArqA","kb_tools_jmeter.md":"CdWyI9Fl","kb_tools_kafka.md":"CWqQJuyL","kb_tools_libreoffice.md":"aLGOy9up","kb_tools_nginx.md":"TXWW9QLU","kb_tools_onlyoffice.md":"C9WmDRua","kb_tools_rabbitmq.md":"ziAH7CNx","kb_tools_rust-desk.md":"UmwoThDs","kb_tools_selenium.md":"DdsCqwoJ","kb_tools_storage.md":"CBEGb_yZ","kb_web_capacitor.md":"Ae_ZWXLu","kb_web_ionic.md":"CZ-d8FKP","kb_web_node.md":"B0fRlrxE","kb_windows_index.md":"gcOaruMa","kb_windows_powershell.md":"DwVnMD1V","kb_windows_vs.md":"ByHhrVTS","kb_windows_wsl.md":"DMG04JMY"}
