{"about_index.md":"BcPdkUPi","blog_dev_ai-posts.md":"Cg5luTX0","blog_first.md":"Chg1quMI","blog_index.md":"CXwtc3gG","index.md":"Bxbiw8RH","kb_index.md":"B0dCOH6Z","kb_java_blog.md":"aH642m0-","kb_java_cloudnative.md":"FElCamZn","kb_java_consul.md":"aHdYMZv4","kb_java_graalvm.md":"DQtC9vqS","kb_java_gradle.md":"DDwhwy6X","kb_java_grafana.md":"CtzVaLP5","kb_java_idea.md":"Bh4uv-TE","kb_java_index.md":"BGk4bgNs","kb_java_jdk.md":"BVGYgxt9","kb_java_jsp.md":"Ck3aDvtk","kb_java_jvm.md":"DfXejwG1","kb_java_maven.md":"CPEUUhQp","kb_java_oauth.md":"DCSHc5Bn","kb_linux_glibc.md":"CCpaX7j9","kb_linux_index.md":"DuQJTRLC","kb_linux_rhel.md":"D5_l7Af9","kb_linux_ubuntu.md":"R2DGEse0","kb_macos_homebrew.md":"BYsoBe-9","kb_macos_index.md":"B7F9ZDQ1","kb_macos_sdkman.md":"BeIqiU17","kb_mariadb_install.md":"dh3chH57","kb_mongo_index.md":"LnxwA4pu","kb_mongo_install.md":"BfdiOVGH","kb_mysql_config.md":"wffL_SKl","kb_mysql_faq.md":"rwj1LyJS","kb_mysql_idx.md":"CihGEK5Y","kb_mysql_index.md":"CZgI55A7","kb_mysql_install.md":"BDNSX40_","kb_mysql_master-slave.md":"DmU-CphU","kb_pgsql_index.md":"DGAvEWJh","kb_pgsql_install.md":"DbU0564m","kb_php_awesome.md":"BFZr7uN-","kb_php_index.md":"HL_VRkRh","kb_python_index.md":"CXFHFN7p","kb_redis_index.md":"_v4cXwIN","kb_redis_install.md":"BoLW58jV","kb_ruby_index.md":"CmqkjEmE","kb_rust_index.md":"Dz5dr-Lw","kb_tools_docker.md":"E9sPF0Uj","kb_tools_editor.md":"B7_0KFRp","kb_tools_elastic.md":"C5jqyjgP","kb_tools_git.md":"iZM8DfDL","kb_tools_github.md":"BCI3vYxp","kb_tools_gitlab.md":"Da_l5Ilw","kb_tools_grafana.md":"D4KR8Ne4","kb_tools_jenkins.md":"BF68aOzD","kb_tools_jmeter.md":"Y1fCe8mA","kb_tools_kafka.md":"DJcYlibl","kb_tools_libreoffice.md":"BlbHRmbw","kb_tools_nginx.md":"VMme2mp8","kb_tools_onlyoffice.md":"Ci9mZbGY","kb_tools_podman.md":"R4dJP5Ab","kb_tools_rabbitmq.md":"DVCZyaYE","kb_tools_rust-desk.md":"BqjiGjyf","kb_tools_selenium.md":"NnXoAn1c","kb_tools_storage.md":"CeYpEULl","kb_tools_terminal.md":"BMYDOTU1","kb_web_capacitor.md":"W2j5eEF_","kb_web_ionic.md":"DlUsRfF-","kb_web_node.md":"DIHS_7wo","kb_windows_index.md":"V2-NW682","kb_windows_powershell.md":"0vkuR9dD","kb_windows_vs.md":"NIaXIrb5","kb_windows_wsl.md":"BSOPFjJF"}
