{"kb_linux_ubuntu.md":"D0orUBUK","kb_macos_homebrew.md":"p3o8K5an","kb_macos_index.md":"-kPIz5CT","kb_mongo_index.md":"BLS9maMM","kb_macos_sdkman.md":"CJp9oBRq","kb_mysql_faq.md":"DTOk4adG","kb_mysql_idx.md":"BdtTT9yu","kb_mysql_index.md":"BCu50DqH","kb_mongo_install.md":"BcYY5x9U","kb_mysql_master-slave.md":"DcQMLZnf","kb_php_awesome.md":"SDNJ3Tek","kb_redis_index.md":"CTlRoTMv","kb_redis_install.md":"CiOzJUeQ","kb_tools_elastic.md":"t7L2YL-Y","kb_tools_git.md":"DVWUpuCm","kb_ruby_index.md":"IWL0-1-E","kb_rust_index.md":"C7hspeho","kb_tools_gitlab.md":"bQ2-FOMh","kb_java_index.md":"DAmI4sjY","kb_java_jdk.md":"BkaNCOlI","kb_java_maven.md":"CVvxp3ol","kb_java_jsp.md":"57beyCh_","blog_tech_video-encrypt.md":"COgd0WUr","blog_first.md":"CcRwhErw","kb_java_oauth.md":"DdA1jC0b","blog_tech_live.md":"B2-xyutN","kb_java_consul.md":"uFqiFGx0","kb_index.md":"Cwo3zZEp","kb_java_gradle.md":"Dde9SVVv","kb_java_idea.md":"BqWRMPKT","about_index.md":"CRC1FaS-","kb_linux_index.md":"-vm80QZF","kb_python_index.md":"De4FM_aQ","kb_tools_jmeter.md":"BcANmVB7","kb_postgresql_index.md":"nNo3rFVm","kb_tools_nginx.md":"DcpIV14C","kb_php_index.md":"BBt0ufdC","kb_mysql_install.md":"CcsZfO7t","kb_tools_docker.md":"DCqB6oLB","kb_tools_libreoffice.md":"CnR2JKF0","kb_tools_github.md":"BOuk4Snx","kb_linux_rhel.md":"B5GxKDlh","kb_java_graalvm.md":"DdUM-ka_","index.md":"BON5F-xm","kb_windows_wsl.md":"BW8MHOsj","kb_web_capacitor.md":"BEud5OKk","kb_web_ionic.md":"DG4Na3RD","kb_tools_jenkins.md":"BGroyTkx","blog_index.md":"DZTEh0SJ","kb_windows_vs.md":"Q71hE1-b","kb_web_node.md":"Da2WdOgh","kb_windows_index.md":"BIbO5TCN","kb_tools_rabbitmq.md":"MaE8w_lC","kb_tools_onlyoffice.md":"CH6bcTqR","kb_postgresql_install.md":"bjjegsvE","kb_tools_kafka.md":"BLJoZt4Q","kb_tools_minio.md":"BRyDcvaA","kb_windows_powershell.md":"DeWR4el3"}
