{"about_index.md":"CpyzlVlT","blog_first.md":"ExH1Cbgo","blog_index.md":"ChUcgaQe","blog_tech_live.md":"BNug58HH","blog_tech_video-encrypt.md":"CcWvTc3E","index.md":"DBJSOKj2","kb_index.md":"BUHvJ4by","kb_java_blog.md":"-RTMErEm","kb_java_consul.md":"DRnvy-Pz","kb_java_graalvm.md":"JrYZ-G9A","kb_java_gradle.md":"Cw6ki4hu","kb_java_idea.md":"DvHoo9C9","kb_java_index.md":"1EpNvKA3","kb_java_jdk.md":"NKBxZnRk","kb_java_jsp.md":"BHo-gz1a","kb_java_jvm.md":"Bu7yjtrv","kb_java_maven.md":"Cadjevad","kb_java_oauth.md":"DWjV9Iqo","kb_linux_index.md":"BA4dHaWP","kb_linux_rhel.md":"B3KRSsch","kb_linux_ubuntu.md":"BNxlr3R6","kb_macos_homebrew.md":"s_l0kas5","kb_macos_index.md":"Bv5wHFgf","kb_macos_sdkman.md":"rF8TkyaZ","kb_mongo_index.md":"Dvk3464B","kb_mongo_install.md":"m0Qzv8TC","kb_mysql_config.md":"DKbMeOdl","kb_mysql_faq.md":"CAYLOO31","kb_mysql_idx.md":"DFH0-Wnn","kb_mysql_index.md":"BGj9sfg3","kb_mysql_install.md":"CWRqUAIj","kb_mysql_master-slave.md":"G1YXNz3G","kb_php_awesome.md":"BljLdh4G","kb_php_index.md":"DJH5oyd0","kb_postgresql_index.md":"DgEFLPs8","kb_postgresql_install.md":"BuD-XXQX","kb_python_index.md":"DF3Z6LUX","kb_redis_index.md":"mZHCifOX","kb_redis_install.md":"U3meq3kf","kb_ruby_index.md":"BnjtIlVU","kb_rust_index.md":"CzoiJ6hl","kb_tools_docker.md":"_AjC5ctZ","kb_tools_elastic.md":"B5rh0PbI","kb_tools_git.md":"DGnl--y1","kb_tools_github.md":"CJahC22l","kb_tools_gitlab.md":"jIw4cXia","kb_tools_jenkins.md":"hvRQ05PV","kb_tools_jmeter.md":"pRCnr-B_","kb_tools_kafka.md":"ByBN-J1s","kb_tools_libreoffice.md":"D58yvz9i","kb_tools_minio.md":"D6Ou5h7b","kb_tools_nginx.md":"Dm9fzkvw","kb_tools_onlyoffice.md":"BZV2ulXn","kb_tools_rabbitmq.md":"DlcQozgd","kb_web_capacitor.md":"7uk9bnev","kb_web_ionic.md":"CvsYZE7A","kb_web_node.md":"Dzp1Uwh5","kb_windows_index.md":"CyAkC7CV","kb_windows_powershell.md":"DANsjJj4","kb_windows_vs.md":"CLrCRrHM","kb_windows_wsl.md":"B0xTiMSv"}
