{"about_index.md":"1f7544ef","blog_first.md":"65ff0720","blog_index.md":"783fc750","blog_tech_live.md":"dbf4ed8c","blog_tech_video-encrypt.md":"dc97de25","index.md":"fb0ebd07","kb_amqp_kafka.md":"5c87d4e6","kb_amqp_rabbitmq.md":"a21dfbf7","kb_java_gradle.md":"6108884f","kb_cloud_docker.md":"34b8e92b","kb_java_idea.md":"1320d83c","kb_cloud_index.md":"b0763266","kb_docs_index.md":"ccdd36c6","kb_java_index.md":"ddd60fc8","kb_elastic_index.md":"f994ccff","kb_amqp_index.md":"85fc9800","kb_docs_libreoffice.md":"d94cd3c5","kb_java_jsp.md":"98f328b9","kb_java_jdk.md":"cf79c545","kb_java_consul.md":"85254a4f","kb_index.md":"89f8aa3c","kb_java_graalvm.md":"b81dedd7","kb_docs_onlyoffice.md":"061415b6","kb_macos_index.md":"1d0e108c","kb_mongo_index.md":"50392b81","kb_mongo_install.md":"fef28f69","kb_mysql_idx.md":"8b024185","kb_mysql_master-slave.md":"6cc4dfe7","kb_java_maven.md":"b3cc2b0c","kb_mysql_index.md":"c25e01d0","kb_mysql_install.md":"bf520c82","kb_linux_index.md":"220f4ee8","kb_macos_homebrew.md":"a34e89e4","kb_php_awesome.md":"91bebc5d","kb_windows_vs.md":"db8f2098","kb_windows_powershell.md":"a115609f","kb_linux_ubuntu.md":"1bc0a7de","kb_php_index.md":"4ae4f081","kb_postgresql_index.md":"97e336af","kb_postgresql_install.md":"5d74e1b7","kb_rust_index.md":"3a8f4087","kb_ruby_index.md":"4271a24b","kb_web_node.md":"ed8cdf33","kb_tools_gitlab.md":"a90466c4","kb_tools_git.md":"603fa96e","kb_tools_jmeter.md":"546165b2","kb_redis_index.md":"1a4e691e","kb_tools_minio.md":"24e7ca27","kb_web_capacitor.md":"fc912387","kb_web_nginx.md":"d3330346","kb_python_index.md":"a71701c2","kb_redis_install.md":"f5a4a256","kb_web_ionic.md":"26107def","kb_linux_rhel.md":"64c4c354","kb_windows_index.md":"968de65e","kb_tools_jenkins.md":"980ff110","kb_web_index.md":"0a35a778","kb_elastic_install.md":"53ab181f","kb_windows_wsl.md":"0e2efbdc"}
