{"about_index.md":"LP4EJz34","blog_first.md":"CtRsSe5Y","blog_index.md":"DWmhVvJX","blog_tech_live.md":"CO3tGapb","blog_tech_video-encrypt.md":"DgwQki5v","index.md":"Eq-bI-8j","kb_index.md":"DyZjzdv7","kb_java_blog.md":"i0afKL8j","kb_java_cloudnative.md":"BdHZUXJc","kb_java_consul.md":"CbkfRxIV","kb_java_graalvm.md":"tQNhupxK","kb_java_gradle.md":"BtsOkI9s","kb_java_grafana.md":"Vmtxlb45","kb_java_idea.md":"DTPrHEoP","kb_java_index.md":"DrnRb6ND","kb_java_jdk.md":"CmsjmlvI","kb_java_jsp.md":"D-XW4nAh","kb_java_jvm.md":"HngB0o2y","kb_java_maven.md":"fK-GloZy","kb_java_oauth.md":"BtyUyK2h","kb_linux_glibc.md":"4Q0OPK5O","kb_linux_index.md":"CHoeZKS_","kb_linux_rhel.md":"DiFYRVNO","kb_linux_ubuntu.md":"D1Kp9Iwl","kb_macos_homebrew.md":"DFkYZCTe","kb_macos_index.md":"D5I1ielE","kb_macos_sdkman.md":"BAvZAju-","kb_mariadb_install.md":"CA5RzI5z","kb_mongo_index.md":"Cwxbs5iO","kb_mongo_install.md":"DdZcNZ6o","kb_mysql_config.md":"DSxpWUS2","kb_mysql_faq.md":"BqcZxtRH","kb_mysql_idx.md":"DUwYdSrY","kb_mysql_index.md":"CwOVTtIv","kb_mysql_install.md":"BkTUo2mF","kb_mysql_master-slave.md":"xU-b_g5A","kb_pgsql_index.md":"MfMD8FKb","kb_pgsql_install.md":"BZSSsU5y","kb_php_awesome.md":"CveUANni","kb_php_index.md":"BL3OG8u7","kb_python_index.md":"BLe5timj","kb_redis_index.md":"Rgkgmjfn","kb_redis_install.md":"DElGjY6f","kb_ruby_index.md":"PoBLIRwn","kb_rust_index.md":"D6CKibkB","kb_tools_docker.md":"stQWSmyB","kb_tools_editor.md":"CRZWkFP0","kb_tools_elastic.md":"CFi7Pgbe","kb_tools_git.md":"BJdA5u62","kb_tools_github.md":"B4BCv5Rz","kb_tools_gitlab.md":"B8h8HVwE","kb_tools_grafana.md":"Cbwc-cdH","kb_tools_jenkins.md":"DdUi-6SW","kb_tools_jmeter.md":"BwqQ2e1C","kb_tools_kafka.md":"BosToHnb","kb_tools_libreoffice.md":"_xbggj_X","kb_tools_nginx.md":"BoNO1mTb","kb_tools_onlyoffice.md":"BHgEiCfw","kb_tools_podman.md":"6Cu3lMTC","kb_tools_rabbitmq.md":"CuoSbgHt","kb_tools_rust-desk.md":"Dcf197pt","kb_tools_selenium.md":"DZB_7yid","kb_tools_storage.md":"BTgbmHsL","kb_tools_terminal.md":"BwXM__50","kb_web_capacitor.md":"BQZAeFwC","kb_web_ionic.md":"CIniAr9S","kb_web_node.md":"Bja6-1ys","kb_windows_index.md":"DizlESu9","kb_windows_powershell.md":"B2PRXyFz","kb_windows_vs.md":"DpG_al6U","kb_windows_wsl.md":"BTum6kU4"}
