{"about_index.md":"CBvB9q9J","blog_first.md":"Duu7vQ3G","blog_index.md":"CjmAb9Qa","blog_tech_live.md":"DQZzX7jS","blog_tech_video-encrypt.md":"C7AOeAwQ","index.md":"oB5-16p0","kb_index.md":"o7tySVMa","kb_java_blog.md":"D25Mn4il","kb_java_cloudnative.md":"DxpX7eNe","kb_java_consul.md":"CYq5ks5f","kb_java_graalvm.md":"DCznSE3T","kb_java_gradle.md":"C_cYmiHs","kb_java_grafana.md":"DnlP6qpz","kb_java_idea.md":"CYhlMJyG","kb_java_index.md":"cb8DtK4C","kb_java_jdk.md":"CadkB0DF","kb_java_jsp.md":"BCwGbrJM","kb_java_jvm.md":"BW0vqbG-","kb_java_maven.md":"0qs2l-AZ","kb_java_oauth.md":"DWBsCRPf","kb_linux_glibc.md":"DiFzGkgC","kb_linux_index.md":"3Spsc3yM","kb_linux_rhel.md":"odxGP7gk","kb_linux_ubuntu.md":"CGZlrJ2J","kb_macos_homebrew.md":"VQDdhcFA","kb_macos_index.md":"DoN3A1Cw","kb_macos_sdkman.md":"C_VBp5A0","kb_mongo_index.md":"CC98EgnR","kb_mongo_install.md":"JIiT0zmj","kb_mysql_config.md":"Dfdlsuw4","kb_mysql_faq.md":"Dvc2sAtE","kb_mysql_idx.md":"CEbdL6_K","kb_mysql_index.md":"Cp2eFDOI","kb_mysql_install.md":"DoYUbzvy","kb_mysql_master-slave.md":"IEvEf89b","kb_php_awesome.md":"CnmEH_VU","kb_php_index.md":"Dr4BtY4Y","kb_postgresql_index.md":"DLpmEF51","kb_postgresql_install.md":"CGFHkNsS","kb_python_index.md":"iY_MSYna","kb_redis_index.md":"C7kkUrIQ","kb_redis_install.md":"5AVRNKlu","kb_ruby_index.md":"1Gk9NMfR","kb_rust_index.md":"DuDhoxiP","kb_tools_docker.md":"fKuzNUxy","kb_tools_editor.md":"DbUFgOYK","kb_tools_elastic.md":"iycHan0A","kb_tools_git.md":"Bz_Vn0PA","kb_tools_github.md":"tiw02A4w","kb_tools_gitlab.md":"DTOU73Lo","kb_tools_grafana.md":"BqmNR185","kb_tools_jenkins.md":"BQrC0kMn","kb_tools_jmeter.md":"_s3qJH5L","kb_tools_kafka.md":"Ci3OAaQN","kb_tools_libreoffice.md":"DIvhLV1S","kb_tools_minio.md":"BfhUNvJ0","kb_tools_nginx.md":"CL1zgGRL","kb_tools_onlyoffice.md":"B6WwE_hC","kb_tools_rabbitmq.md":"BZnW_22Z","kb_tools_rust-desk.md":"V8l0RS0Z","kb_tools_selenium.md":"BlJvpInm","kb_web_capacitor.md":"B0bW2IBc","kb_web_ionic.md":"C_cm2nmO","kb_web_node.md":"HmB7YKVS","kb_windows_index.md":"CbDR_YqS","kb_windows_powershell.md":"CDP1VAZb","kb_windows_vs.md":"Ckp2MOZc","kb_windows_wsl.md":"CGZVzJT2"}
